LICENSE
README.md
setup.cfg
setup.py
PyCrawlerX/__init__.py
PyCrawlerX/pycrawlerx.py
PyCrawlerX.egg-info/PKG-INFO
PyCrawlerX.egg-info/SOURCES.txt
PyCrawlerX.egg-info/dependency_links.txt
PyCrawlerX.egg-info/top_level.txt
PyCrawlerX.egg-info/zip-safe