Metadata-Version: 2.1
Name: PyCrawlerX
Version: 0.0.2
Summary: PyCrawlerX is a Python CLI tool to crawl through directories and execute files.
Home-page: https://github.com/4akhilkumar/pycrawlerx
Author: Sai Akhil Kumar Reddy N
Author-email: 4akhilkumar@gmail.com
License: MIT
Keywords: Python,Directory,Files,Execution,PyCrawlerX,CLI,Command Line Interface,Menu
Classifier: Development Status :: 4 - Beta
Classifier: Intended Audience :: Developers
Classifier: License :: OSI Approved :: MIT License
Classifier: Programming Language :: Python :: 3
Classifier: Programming Language :: Python :: 3.7
Classifier: Programming Language :: Python :: 3.8
Classifier: Programming Language :: Python :: 3.9
Classifier: Programming Language :: Python :: 3.10
Classifier: Programming Language :: Python :: 3.11
License-File: LICENSE
